[
  {"name":"北京","admin1":"北京市","lat":39.9042,"lon":116.4074,"country":"中国"},
  {"name":"上海","admin1":"上海市","lat":31.2304,"lon":121.4737,"country":"中国"},
  {"name":"天津","admin1":"天津市","lat":39.3434,"lon":117.3616,"country":"中国"},
  {"name":"重庆","admin1":"重庆市","lat":29.4316,"lon":106.9123,"country":"中国"},
  {"name":"石家庄","admin1":"河北省","lat":38.0428,"lon":114.5149,"country":"中国"},
  {"name":"唐山","admin1":"河北省","lat":39.6309,"lon":118.1802,"country":"中国"},
  {"name":"秦皇岛","admin1":"河北省","lat":39.8887,"lon":119.5950,"country":"中国"},
  {"name":"邯郸","admin1":"河北省","lat":36.6256,"lon":114.5391,"country":"中国"},
  {"name":"邢台","admin1":"河北省","lat":37.0507,"lon":114.5044,"country":"中国"},
  {"name":"保定","admin1":"河北省","lat":38.8739,"lon":115.4646,"country":"中国"},
  {"name":"张家口","admin1":"河北省","lat":40.7678,"lon":114.8863,"country":"中国"},
  {"name":"承德","admin1":"河北省","lat":40.9515,"lon":117.9634,"country":"中国"},
  {"name":"沧州","admin1":"河北省","lat":38.3038,"lon":116.8575,"country":"中国"},
  {"name":"廊坊","admin1":"河北省","lat":39.5379,"lon":116.6838,"country":"中国"},
  {"name":"衡水","admin1":"河北省","lat":37.7389,"lon":115.6862,"country":"中国"},
  {"name":"太原","admin1":"山西省","lat":37.8706,"lon":112.5489,"country":"中国"},
  {"name":"大同","admin1":"山西省","lat":40.0768,"lon":113.3001,"country":"中国"},
  {"name":"阳泉","admin1":"山西省","lat":37.8567,"lon":113.5805,"country":"中国"},
  {"name":"长治","admin1":"山西省","lat":36.1955,"lon":113.1203,"country":"中国"},
  {"name":"晋城","admin1":"山西省","lat":35.4904,"lon":112.8513,"country":"中国"},
  {"name":"朔州","admin1":"山西省","lat":39.3316,"lon":112.4328,"country":"中国"},
  {"name":"晋中","admin1":"山西省","lat":37.6870,"lon":112.7527,"country":"中国"},
  {"name":"运城","admin1":"山西省","lat":35.0265,"lon":111.0069,"country":"中国"},
  {"name":"忻州","admin1":"山西省","lat":38.4167,"lon":112.7342,"country":"中国"},
  {"name":"临汾","admin1":"山西省","lat":36.0880,"lon":111.5189,"country":"中国"},
  {"name":"吕梁","admin1":"山西省","lat":37.5183,"lon":111.1432,"country":"中国"},
  {"name":"呼和浩特","admin1":"内蒙古","lat":40.8174,"lon":111.7652,"country":"中国"},
  {"name":"包头","admin1":"内蒙古","lat":40.6572,"lon":109.8403,"country":"中国"},
  {"name":"乌海","admin1":"内蒙古","lat":39.6534,"lon":106.7956,"country":"中国"},
  {"name":"赤峰","admin1":"内蒙古","lat":42.2568,"lon":118.8868,"country":"中国"},
  {"name":"通辽","admin1":"内蒙古","lat":43.6326,"lon":122.2551,"country":"中国"},
  {"name":"鄂尔多斯","admin1":"内蒙古","lat":39.6083,"lon":109.7933,"country":"中国"},
  {"name":"呼伦贝尔","admin1":"内蒙古","lat":49.2120,"lon":119.7695,"country":"中国"},
  {"name":"沈阳","admin1":"辽宁省","lat":41.8057,"lon":123.4315,"country":"中国"},
  {"name":"大连","admin1":"辽宁省","lat":38.9137,"lon":121.6148,"country":"中国"},
  {"name":"鞍山","admin1":"辽宁省","lat":41.1084,"lon":122.9942,"country":"中国"},
  {"name":"抚顺","admin1":"辽宁省","lat":41.8796,"lon":123.9572,"country":"中国"},
  {"name":"本溪","admin1":"辽宁省","lat":41.2943,"lon":123.7668,"country":"中国"},
  {"name":"丹东","admin1":"辽宁省","lat":40.1239,"lon":124.3547,"country":"中国"},
  {"name":"锦州","admin1":"辽宁省","lat":41.1306,"lon":121.1273,"country":"中国"},
  {"name":"营口","admin1":"辽宁省","lat":40.6666,"lon":122.2344,"country":"中国"},
  {"name":"阜新","admin1":"辽宁省","lat":42.0207,"lon":121.6703,"country":"中国"},
  {"name":"辽阳","admin1":"辽宁省","lat":41.2680,"lon":123.2369,"country":"中国"},
  {"name":"盘锦","admin1":"辽宁省","lat":41.1400,"lon":122.0709,"country":"中国"},
  {"name":"铁岭","admin1":"辽宁省","lat":42.2238,"lon":123.7260,"country":"中国"},
  {"name":"朝阳","admin1":"辽宁省","lat":41.5736,"lon":120.4508,"country":"中国"},
  {"name":"葫芦岛","admin1":"辽宁省","lat":40.7109,"lon":120.8367,"country":"中国"},
  {"name":"长春","admin1":"吉林省","lat":43.8961,"lon":125.3265,"country":"中国"},
  {"name":"吉林","admin1":"吉林省","lat":43.8379,"lon":126.5490,"country":"中国"},
  {"name":"四平","admin1":"吉林省","lat":43.1664,"lon":124.3503,"country":"中国"},
  {"name":"辽源","admin1":"吉林省","lat":42.8880,"lon":125.1447,"country":"中国"},
  {"name":"通化","admin1":"吉林省","lat":41.7282,"lon":125.9398,"country":"中国"},
  {"name":"白山","admin1":"吉林省","lat":41.9399,"lon":126.4239,"country":"中国"},
  {"name":"松原","admin1":"吉林省","lat":45.1416,"lon":124.8252,"country":"中国"},
  {"name":"白城","admin1":"吉林省","lat":45.6195,"lon":122.8387,"country":"中国"},
  {"name":"哈尔滨","admin1":"黑龙江省","lat":45.8038,"lon":126.5350,"country":"中国"},
  {"name":"齐齐哈尔","admin1":"黑龙江省","lat":47.3543,"lon":123.9182,"country":"中国"},
  {"name":"鸡西","admin1":"黑龙江省","lat":45.2950,"lon":130.9694,"country":"中国"},
  {"name":"鹤岗","admin1":"黑龙江省","lat":47.3502,"lon":130.2977,"country":"中国"},
  {"name":"双鸭山","admin1":"黑龙江省","lat":46.6467,"lon":131.1590,"country":"中国"},
  {"name":"大庆","admin1":"黑龙江省","lat":46.5907,"lon":125.1039,"country":"中国"},
  {"name":"伊春","admin1":"黑龙江省","lat":47.7276,"lon":128.8410,"country":"中国"},
  {"name":"佳木斯","admin1":"黑龙江省","lat":46.7999,"lon":130.3189,"country":"中国"},
  {"name":"七台河","admin1":"黑龙江省","lat":45.7718,"lon":131.0031,"country":"中国"},
  {"name":"牡丹江","admin1":"黑龙江省","lat":44.5517,"lon":129.6326,"country":"中国"},
  {"name":"黑河","admin1":"黑龙江省","lat":50.2390,"lon":127.4990,"country":"中国"},
  {"name":"绥化","admin1":"黑龙江省","lat":46.6525,"lon":126.9693,"country":"中国"},
  {"name":"南京","admin1":"江苏省","lat":32.0603,"lon":118.7969,"country":"中国"},
  {"name":"无锡","admin1":"江苏省","lat":31.4901,"lon":120.3121,"country":"中国"},
  {"name":"徐州","admin1":"江苏省","lat":34.2044,"lon":117.2852,"country":"中国"},
  {"name":"常州","admin1":"江苏省","lat":31.7713,"lon":119.9742,"country":"中国"},
  {"name":"苏州","admin1":"江苏省","lat":31.2990,"lon":120.5853,"country":"中国"},
  {"name":"南通","admin1":"江苏省","lat":31.9796,"lon":120.8937,"country":"中国"},
  {"name":"连云港","admin1":"江苏省","lat":34.5965,"lon":119.2215,"country":"中国"},
  {"name":"淮安","admin1":"江苏省","lat":33.6104,"lon":119.0153,"country":"中国"},
  {"name":"盐城","admin1":"江苏省","lat":33.3474,"lon":120.1633,"country":"中国"},
  {"name":"扬州","admin1":"江苏省","lat":32.3932,"lon":119.4140,"country":"中国"},
  {"name":"镇江","admin1":"江苏省","lat":32.1910,"lon":119.4248,"country":"中国"},
  {"name":"泰州","admin1":"江苏省","lat":32.4563,"lon":119.9228,"country":"中国"},
  {"name":"宿迁","admin1":"江苏省","lat":33.9631,"lon":118.2755,"country":"中国"},
  {"name":"杭州","admin1":"浙江省","lat":30.2741,"lon":120.1551,"country":"中国"},
  {"name":"宁波","admin1":"浙江省","lat":29.8683,"lon":121.5440,"country":"中国"},
  {"name":"温州","admin1":"浙江省","lat":27.9939,"lon":120.6994,"country":"中国"},
  {"name":"嘉兴","admin1":"浙江省","lat":30.7710,"lon":120.7551,"country":"中国"},
  {"name":"湖州","admin1":"浙江省","lat":30.8938,"lon":120.0881,"country":"中国"},
  {"name":"绍兴","admin1":"浙江省","lat":30.0024,"lon":120.5820,"country":"中国"},
  {"name":"金华","admin1":"浙江省","lat":29.1022,"lon":119.6476,"country":"中国"},
  {"name":"衢州","admin1":"浙江省","lat":28.9362,"lon":118.8753,"country":"中国"},
  {"name":"舟山","admin1":"浙江省","lat":29.9856,"lon":122.2079,"country":"中国"},
  {"name":"台州","admin1":"浙江省","lat":28.6565,"lon":121.4209,"country":"中国"},
  {"name":"丽水","admin1":"浙江省","lat":28.4672,"lon":119.9229,"country":"中国"},
  {"name":"合肥","admin1":"安徽省","lat":31.8206,"lon":117.2272,"country":"中国"},
  {"name":"芜湖","admin1":"安徽省","lat":31.3529,"lon":118.4329,"country":"中国"},
  {"name":"蚌埠","admin1":"安徽省","lat":32.9155,"lon":117.3892,"country":"中国"},
  {"name":"淮南","admin1":"安徽省","lat":32.6255,"lon":116.9998,"country":"中国"},
  {"name":"马鞍山","admin1":"安徽省","lat":31.6908,"lon":118.5062,"country":"中国"},
  {"name":"淮北","admin1":"安徽省","lat":33.9558,"lon":116.7983,"country":"中国"},
  {"name":"铜陵","admin1":"安徽省","lat":30.9453,"lon":117.8124,"country":"中国"},
  {"name":"安庆","admin1":"安徽省","lat":30.5319,"lon":117.0587,"country":"中国"},
  {"name":"黄山","admin1":"安徽省","lat":29.7152,"lon":118.3375,"country":"中国"},
  {"name":"滁州","admin1":"安徽省","lat":32.3071,"lon":118.3172,"country":"中国"},
  {"name":"阜阳","admin1":"安徽省","lat":32.8897,"lon":115.8140,"country":"中国"},
  {"name":"宿州","admin1":"安徽省","lat":33.6462,"lon":116.9639,"country":"中国"},
  {"name":"六安","admin1":"安徽省","lat":31.7356,"lon":116.5219,"country":"中国"},
  {"name":"亳州","admin1":"安徽省","lat":33.8446,"lon":115.7786,"country":"中国"},
  {"name":"池州","admin1":"安徽省","lat":30.6656,"lon":117.4914,"country":"中国"},
  {"name":"宣城","admin1":"安徽省","lat":30.9400,"lon":118.7560,"country":"中国"},
  {"name":"福州","admin1":"福建省","lat":26.0742,"lon":119.2965,"country":"中国"},
  {"name":"厦门","admin1":"福建省","lat":24.4798,"lon":118.0894,"country":"中国"},
  {"name":"莆田","admin1":"福建省","lat":25.4540,"lon":119.0078,"country":"中国"},
  {"name":"三明","admin1":"福建省","lat":26.2634,"lon":117.6392,"country":"中国"},
  {"name":"泉州","admin1":"福建省","lat":24.8744,"lon":118.6760,"country":"中国"},
  {"name":"漳州","admin1":"福建省","lat":24.5134,"lon":117.6474,"country":"中国"},
  {"name":"南平","admin1":"福建省","lat":26.6416,"lon":118.1754,"country":"中国"},
  {"name":"龙岩","admin1":"福建省","lat":25.0966,"lon":117.0175,"country":"中国"},
  {"name":"宁德","admin1":"福建省","lat":26.6615,"lon":119.5472,"country":"中国"},
  {"name":"南昌","admin1":"江西省","lat":28.6829,"lon":115.8582,"country":"中国"},
  {"name":"景德镇","admin1":"江西省","lat":29.2928,"lon":117.1763,"country":"中国"},
  {"name":"萍乡","admin1":"江西省","lat":27.6228,"lon":113.8543,"country":"中国"},
  {"name":"九江","admin1":"江西省","lat":29.7186,"lon":115.9985,"country":"中国"},
  {"name":"新余","admin1":"江西省","lat":27.8185,"lon":114.9170,"country":"中国"},
  {"name":"鹰潭","admin1":"江西省","lat":28.2603,"lon":117.0354,"country":"中国"},
  {"name":"赣州","admin1":"江西省","lat":25.8315,"lon":114.9349,"country":"中国"},
  {"name":"吉安","admin1":"江西省","lat":27.1138,"lon":114.9929,"country":"中国"},
  {"name":"宜春","admin1":"江西省","lat":27.8144,"lon":114.4158,"country":"中国"},
  {"name":"抚州","admin1":"江西省","lat":27.9479,"lon":116.3583,"country":"中国"},
  {"name":"上饶","admin1":"江西省","lat":28.4546,"lon":117.9498,"country":"中国"},
  {"name":"济南","admin1":"山东省","lat":36.6512,"lon":117.1201,"country":"中国"},
  {"name":"青岛","admin1":"山东省","lat":36.0671,"lon":120.3826,"country":"中国"},
  {"name":"淄博","admin1":"山东省","lat":36.8134,"lon":118.0549,"country":"中国"},
  {"name":"枣庄","admin1":"山东省","lat":34.8108,"lon":117.3211,"country":"中国"},
  {"name":"东营","admin1":"山东省","lat":37.4337,"lon":118.6746,"country":"中国"},
  {"name":"烟台","admin1":"山东省","lat":37.4635,"lon":121.4479,"country":"中国"},
  {"name":"潍坊","admin1":"山东省","lat":36.7069,"lon":119.1619,"country":"中国"},
  {"name":"济宁","admin1":"山东省","lat":35.4148,"lon":116.5872,"country":"中国"},
  {"name":"泰安","admin1":"山东省","lat":36.2004,"lon":117.0874,"country":"中国"},
  {"name":"威海","admin1":"山东省","lat":37.5130,"lon":122.1218,"country":"中国"},
  {"name":"日照","admin1":"山东省","lat":35.4164,"lon":119.5269,"country":"中国"},
  {"name":"临沂","admin1":"山东省","lat":35.1047,"lon":118.3564,"country":"中国"},
  {"name":"德州","admin1":"山东省","lat":37.4357,"lon":116.3595,"country":"中国"},
  {"name":"聊城","admin1":"山东省","lat":36.4570,"lon":115.9854,"country":"中国"},
  {"name":"滨州","admin1":"山东省","lat":37.4346,"lon":117.9729,"country":"中国"},
  {"name":"菏泽","admin1":"山东省","lat":35.2336,"lon":115.4812,"country":"中国"},
  {"name":"郑州","admin1":"河南省","lat":34.7473,"lon":113.6249,"country":"中国"},
  {"name":"开封","admin1":"河南省","lat":34.7973,"lon":114.3074,"country":"中国"},
  {"name":"洛阳","admin1":"河南省","lat":34.6196,"lon":112.4540,"country":"中国"},
  {"name":"平顶山","admin1":"河南省","lat":33.7665,"lon":113.1925,"country":"中国"},
  {"name":"安阳","admin1":"河南省","lat":36.1002,"lon":114.3938,"country":"中国"},
  {"name":"鹤壁","admin1":"河南省","lat":35.7478,"lon":114.2973,"country":"中国"},
  {"name":"新乡","admin1":"河南省","lat":35.3032,"lon":113.9270,"country":"中国"},
  {"name":"焦作","admin1":"河南省","lat":35.2157,"lon":113.2425,"country":"中国"},
  {"name":"濮阳","admin1":"河南省","lat":35.7618,"lon":115.0294,"country":"中国"},
  {"name":"许昌","admin1":"河南省","lat":34.0355,"lon":113.8525,"country":"中国"},
  {"name":"漯河","admin1":"河南省","lat":33.5807,"lon":114.0170,"country":"中国"},
  {"name":"三门峡","admin1":"河南省","lat":34.7733,"lon":111.2004,"country":"中国"},
  {"name":"南阳","admin1":"河南省","lat":32.9908,"lon":112.5289,"country":"中国"},
  {"name":"商丘","admin1":"河南省","lat":34.4144,"lon":115.6416,"country":"中国"},
  {"name":"信阳","admin1":"河南省","lat":32.1480,"lon":114.0913,"country":"中国"},
  {"name":"周口","admin1":"河南省","lat":33.6258,"lon":114.6962,"country":"中国"},
  {"name":"驻马店","admin1":"河南省","lat":32.9835,"lon":114.0213,"country":"中国"},
  {"name":"武汉","admin1":"湖北省","lat":30.5928,"lon":114.3055,"country":"中国"},
  {"name":"黄石","admin1":"湖北省","lat":30.2202,"lon":115.0771,"country":"中国"},
  {"name":"十堰","admin1":"湖北省","lat":32.6292,"lon":110.7980,"country":"中国"},
  {"name":"宜昌","admin1":"湖北省","lat":30.6925,"lon":111.2868,"country":"中国"},
  {"name":"襄阳","admin1":"湖北省","lat":32.0090,"lon":112.1224,"country":"中国"},
  {"name":"鄂州","admin1":"湖北省","lat":30.3913,"lon":114.8950,"country":"中国"},
  {"name":"荆门","admin1":"湖北省","lat":31.0354,"lon":112.1942,"country":"中国"},
  {"name":"孝感","admin1":"湖北省","lat":30.9248,"lon":113.9167,"country":"中国"},
  {"name":"荆州","admin1":"湖北省","lat":30.3348,"lon":112.2410,"country":"中国"},
  {"name":"黄冈","admin1":"湖北省","lat":30.4470,"lon":114.8721,"country":"中国"},
  {"name":"咸宁","admin1":"湖北省","lat":29.8326,"lon":114.3290,"country":"中国"},
  {"name":"随州","admin1":"湖北省","lat":31.6900,"lon":113.3795,"country":"中国"},
  {"name":"长沙","admin1":"湖南省","lat":28.1281,"lon":112.9388,"country":"中国"},
  {"name":"株洲","admin1":"湖南省","lat":27.8281,"lon":113.1340,"country":"中国"},
  {"name":"湘潭","admin1":"湖南省","lat":27.8362,"lon":112.9263,"country":"中国"},
  {"name":"衡阳","admin1":"湖南省","lat":26.8931,"lon":112.5718,"country":"中国"},
  {"name":"邵阳","admin1":"湖南省","lat":27.2427,"lon":111.4678,"country":"中国"},
  {"name":"岳阳","admin1":"湖南省","lat":29.3572,"lon":113.1288,"country":"中国"},
  {"name":"常德","admin1":"湖南省","lat":29.0313,"lon":111.6986,"country":"中国"},
  {"name":"张家界","admin1":"湖南省","lat":29.1171,"lon":110.4791,"country":"中国"},
  {"name":"益阳","admin1":"湖南省","lat":28.5541,"lon":112.3551,"country":"中国"},
  {"name":"郴州","admin1":"湖南省","lat":25.7705,"lon":113.0150,"country":"中国"},
  {"name":"永州","admin1":"湖南省","lat":26.4200,"lon":111.6127,"country":"中国"},
  {"name":"怀化","admin1":"湖南省","lat":27.5695,"lon":109.9972,"country":"中国"},
  {"name":"娄底","admin1":"湖南省","lat":27.7002,"lon":111.9941,"country":"中国"},
  {"name":"广州","admin1":"广东省","lat":23.1291,"lon":113.2644,"country":"中国"},
  {"name":"韶关","admin1":"广东省","lat":24.8104,"lon":113.5978,"country":"中国"},
  {"name":"深圳","admin1":"广东省","lat":22.5431,"lon":114.0579,"country":"中国"},
  {"name":"珠海","admin1":"广东省","lat":22.2710,"lon":113.5767,"country":"中国"},
  {"name":"汕头","admin1":"广东省","lat":23.3541,"lon":116.6822,"country":"中国"},
  {"name":"佛山","admin1":"广东省","lat":23.0219,"lon":113.1219,"country":"中国"},
  {"name":"江门","admin1":"广东省","lat":22.5791,"lon":113.0786,"country":"中国"},
  {"name":"湛江","admin1":"广东省","lat":21.2707,"lon":110.3588,"country":"中国"},
  {"name":"茂名","admin1":"广东省","lat":21.6633,"lon":110.9252,"country":"中国"},
  {"name":"肇庆","admin1":"广东省","lat":23.0472,"lon":112.4658,"country":"中国"},
  {"name":"惠州","admin1":"广东省","lat":23.1107,"lon":114.4162,"country":"中国"},
  {"name":"梅州","admin1":"广东省","lat":24.3049,"lon":116.1221,"country":"中国"},
  {"name":"汕尾","admin1":"广东省","lat":22.7860,"lon":115.3736,"country":"中国"},
  {"name":"河源","admin1":"广东省","lat":23.7442,"lon":114.6922,"country":"中国"},
  {"name":"阳江","admin1":"广东省","lat":21.8584,"lon":111.9828,"country":"中国"},
  {"name":"清远","admin1":"广东省","lat":23.6820,"lon":113.0560,"country":"中国"},
  {"name":"东莞","admin1":"广东省","lat":23.0208,"lon":113.7518,"country":"中国"},
  {"name":"中山","admin1":"广东省","lat":22.5171,"lon":113.3926,"country":"中国"},
  {"name":"潮州","admin1":"广东省","lat":23.6571,"lon":116.6224,"country":"中国"},
  {"name":"揭阳","admin1":"广东省","lat":23.5489,"lon":116.3728,"country":"中国"},
  {"name":"云浮","admin1":"广东省","lat":22.9151,"lon":112.0441,"country":"中国"},
  {"name":"南宁","admin1":"广西壮族自治区","lat":22.8170,"lon":108.3665,"country":"中国"},
  {"name":"柳州","admin1":"广西壮族自治区","lat":24.3260,"lon":109.4156,"country":"中国"},
  {"name":"桂林","admin1":"广西壮族自治区","lat":25.2736,"lon":110.2900,"country":"中国"},
  {"name":"梧州","admin1":"广西壮族自治区","lat":23.4773,"lon":111.2786,"country":"中国"},
  {"name":"北海","admin1":"广西壮族自治区","lat":21.4816,"lon":109.1207,"country":"中国"},
  {"name":"防城港","admin1":"广西壮族自治区","lat":21.6869,"lon":108.3536,"country":"中国"},
  {"name":"钦州","admin1":"广西壮族自治区","lat":21.9797,"lon":108.6542,"country":"中国"},
  {"name":"贵港","admin1":"广西壮族自治区","lat":23.1131,"lon":109.5980,"country":"中国"},
  {"name":"玉林","admin1":"广西壮族自治区","lat":22.6555,"lon":110.1556,"country":"中国"},
  {"name":"百色","admin1":"广西壮族自治区","lat":23.9024,"lon":106.6194,"country":"中国"},
  {"name":"贺州","admin1":"广西壮族自治区","lat":24.4036,"lon":111.5668,"country":"中国"},
  {"name":"河池","admin1":"广西壮族自治区","lat":24.6935,"lon":108.0854,"country":"中国"},
  {"name":"来宾","admin1":"广西壮族自治区","lat":23.7419,"lon":109.2219,"country":"中国"},
  {"name":"崇左","admin1":"广西壮族自治区","lat":22.3786,"lon":107.3648,"country":"中国"},
  {"name":"海口","admin1":"海南省","lat":20.0440,"lon":110.3495,"country":"中国"},
  {"name":"三亚","admin1":"海南省","lat":18.2528,"lon":109.5119,"country":"中国"},
  {"name":"三沙","admin1":"海南省","lat":16.8314,"lon":112.3281,"country":"中国"},
  {"name":"儋州","admin1":"海南省","lat":19.5219,"lon":109.5806,"country":"中国"},
  {"name":"成都","admin1":"四川省","lat":30.5728,"lon":104.0668,"country":"中国"},
  {"name":"自贡","admin1":"四川省","lat":29.3394,"lon":104.7784,"country":"中国"},
  {"name":"攀枝花","admin1":"四川省","lat":26.5820,"lon":101.7187,"country":"中国"},
  {"name":"泸州","admin1":"四川省","lat":28.8958,"lon":105.4434,"country":"中国"},
  {"name":"德阳","admin1":"四川省","lat":31.1271,"lon":104.3980,"country":"中国"},
  {"name":"绵阳","admin1":"四川省","lat":31.4670,"lon":104.6796,"country":"中国"},
  {"name":"广元","admin1":"四川省","lat":32.4335,"lon":105.8442,"country":"中国"},
  {"name":"遂宁","admin1":"四川省","lat":30.5069,"lon":105.5930,"country":"中国"},
  {"name":"内江","admin1":"四川省","lat":29.5936,"lon":105.0585,"country":"中国"},
  {"name":"乐山","admin1":"四川省","lat":29.5824,"lon":103.7651,"country":"中国"},
  {"name":"南充","admin1":"四川省","lat":30.7951,"lon":106.1070,"country":"中国"},
  {"name":"眉山","admin1":"四川省","lat":30.0741,"lon":103.8270,"country":"中国"},
  {"name":"宜宾","admin1":"四川省","lat":28.7522,"lon":104.6205,"country":"中国"},
  {"name":"广安","admin1":"四川省","lat":30.4563,"lon":106.6295,"country":"中国"},
  {"name":"达州","admin1":"四川省","lat":31.2096,"lon":107.5095,"country":"中国"},
  {"name":"雅安","admin1":"四川省","lat":30.0114,"lon":103.0400,"country":"中国"},
  {"name":"巴中","admin1":"四川省","lat":31.8670,"lon":106.7481,"country":"中国"},
  {"name":"资阳","admin1":"四川省","lat":30.1061,"lon":104.6554,"country":"中国"},
  {"name":"贵阳","admin1":"贵州省","lat":26.6470,"lon":106.6302,"country":"中国"},
  {"name":"六盘水","admin1":"贵州省","lat":26.5934,"lon":104.8301,"country":"中国"},
  {"name":"遵义","admin1":"贵州省","lat":27.7254,"lon":106.9271,"country":"中国"},
  {"name":"安顺","admin1":"贵州省","lat":26.2533,"lon":105.9474,"country":"中国"},
  {"name":"毕节","admin1":"贵州省","lat":27.2844,"lon":105.2920,"country":"中国"},
  {"name":"铜仁","admin1":"贵州省","lat":27.7314,"lon":109.1916,"country":"中国"},
  {"name":"昆明","admin1":"云南省","lat":25.0389,"lon":102.7063,"country":"中国"},
  {"name":"曲靖","admin1":"云南省","lat":25.4901,"lon":103.7963,"country":"中国"},
  {"name":"玉溪","admin1":"云南省","lat":24.3522,"lon":102.5460,"country":"中国"},
  {"name":"保山","admin1":"云南省","lat":25.1140,"lon":99.1621,"country":"中国"},
  {"name":"昭通","admin1":"云南省","lat":27.3382,"lon":103.7174,"country":"中国"},
  {"name":"丽江","admin1":"云南省","lat":26.8720,"lon":100.2299,"country":"中国"},
  {"name":"普洱","admin1":"云南省","lat":22.8252,"lon":100.9669,"country":"中国"},
  {"name":"临沧","admin1":"云南省","lat":23.8844,"lon":100.0893,"country":"中国"},
  {"name":"大理","admin1":"云南省","lat":25.5920,"lon":100.2304,"country":"中国"},
  {"name":"红河","admin1":"云南省","lat":23.3656,"lon":103.3756,"country":"中国"},
  {"name":"文山","admin1":"云南省","lat":23.3983,"lon":104.2155,"country":"中国"},
  {"name":"西双版纳","admin1":"云南省","lat":22.0089,"lon":100.7973,"country":"中国"},
  {"name":"拉萨","admin1":"西藏自治区","lat":29.6501,"lon":91.1164,"country":"中国"},
  {"name":"日喀则","admin1":"西藏自治区","lat":29.2754,"lon":88.8800,"country":"中国"},
  {"name":"昌都","admin1":"西藏自治区","lat":31.1400,"lon":97.1774,"country":"中国"},
  {"name":"林芝","admin1":"西藏自治区","lat":29.6548,"lon":94.3626,"country":"中国"},
  {"name":"山南","admin1":"西藏自治区","lat":29.2394,"lon":91.7663,"country":"中国"},
  {"name":"那曲","admin1":"西藏自治区","lat":31.4800,"lon":92.0565,"country":"中国"},
  {"name":"西安","admin1":"陕西省","lat":34.3416,"lon":108.9398,"country":"中国"},
  {"name":"铜川","admin1":"陕西省","lat":34.8966,"lon":108.9445,"country":"中国"},
  {"name":"宝鸡","admin1":"陕西省","lat":34.3647,"lon":107.2366,"country":"中国"},
  {"name":"咸阳","admin1":"陕西省","lat":34.3296,"lon":108.7086,"country":"中国"},
  {"name":"渭南","admin1":"陕西省","lat":34.5204,"lon":109.5104,"country":"中国"},
  {"name":"延安","admin1":"陕西省","lat":36.6512,"lon":109.4896,"country":"中国"},
  {"name":"汉中","admin1":"陕西省","lat":33.0890,"lon":107.0234,"country":"中国"},
  {"name":"榆林","admin1":"陕西省","lat":38.2902,"lon":109.7345,"country":"中国"},
  {"name":"安康","admin1":"陕西省","lat":32.6849,"lon":109.0290,"country":"中国"},
  {"name":"商洛","admin1":"陕西省","lat":33.8738,"lon":109.9185,"country":"中国"},
  {"name":"兰州","admin1":"甘肃省","lat":36.0611,"lon":103.8343,"country":"中国"},
  {"name":"嘉峪关","admin1":"甘肃省","lat":39.7730,"lon":98.2899,"country":"中国"},
  {"name":"金昌","admin1":"甘肃省","lat":38.5214,"lon":102.1790,"country":"中国"},
  {"name":"白银","admin1":"甘肃省","lat":36.5452,"lon":104.1384,"country":"中国"},
  {"name":"天水","admin1":"甘肃省","lat":34.5811,"lon":105.7058,"country":"中国"},
  {"name":"武威","admin1":"甘肃省","lat":37.9281,"lon":102.6381,"country":"中国"},
  {"name":"张掖","admin1":"甘肃省","lat":38.9256,"lon":100.4497,"country":"中国"},
  {"name":"平凉","admin1":"甘肃省","lat":35.5431,"lon":106.6652,"country":"中国"},
  {"name":"酒泉","admin1":"甘肃省","lat":39.7333,"lon":98.4939,"country":"中国"},
  {"name":"庆阳","admin1":"甘肃省","lat":35.7098,"lon":107.6437,"country":"中国"},
  {"name":"定西","admin1":"甘肃省","lat":35.5809,"lon":104.6266,"country":"中国"},
  {"name":"陇南","admin1":"甘肃省","lat":33.3700,"lon":104.9290,"country":"中国"},
  {"name":"西宁","admin1":"青海省","lat":36.6171,"lon":101.7782,"country":"中国"},
  {"name":"海东","admin1":"青海省","lat":36.4732,"lon":102.1047,"country":"中国"},
  {"name":"银川","admin1":"宁夏回族自治区","lat":38.4864,"lon":106.2324,"country":"中国"},
  {"name":"石嘴山","admin1":"宁夏回族自治区","lat":39.0194,"lon":106.3813,"country":"中国"},
  {"name":"吴忠","admin1":"宁夏回族自治区","lat":37.5000,"lon":106.2080,"country":"中国"},
  {"name":"固原","admin1":"宁夏回族自治区","lat":36.0058,"lon":106.2850,"country":"中国"},
  {"name":"中卫","admin1":"宁夏回族自治区","lat":37.5165,"lon":105.2015,"country":"中国"},
  {"name":"乌鲁木齐","admin1":"新疆维吾尔自治区","lat":43.8256,"lon":87.6168,"country":"中国"},
  {"name":"克拉玛依","admin1":"新疆维吾尔自治区","lat":45.5867,"lon":84.8823,"country":"中国"},
  {"name":"吐鲁番","admin1":"新疆维吾尔自治区","lat":42.9491,"lon":89.1782,"country":"中国"},
  {"name":"哈密","admin1":"新疆维吾尔自治区","lat":42.8194,"lon":93.5140,"country":"中国"},
  {"name":"昌吉","admin1":"新疆维吾尔自治区","lat":44.0071,"lon":87.3081,"country":"中国"},
  {"name":"库尔勒","admin1":"新疆维吾尔自治区","lat":41.7639,"lon":86.1460,"country":"中国"},
  {"name":"阿克苏","admin1":"新疆维吾尔自治区","lat":41.1693,"lon":80.2640,"country":"中国"},
  {"name":"喀什","admin1":"新疆维吾尔自治区","lat":39.4662,"lon":75.9890,"country":"中国"},
  {"name":"伊宁","admin1":"新疆维吾尔自治区","lat":43.9165,"lon":81.3168,"country":"中国"},
  {"name":"石河子","admin1":"新疆维吾尔自治区","lat":44.3060,"lon":86.0723,"country":"中国"},
  {"name":"香港","admin1":"香港特别行政区","lat":22.3193,"lon":114.1694,"country":"中国"},
  {"name":"澳门","admin1":"澳门特别行政区","lat":22.1987,"lon":113.5492,"country":"中国"},
  {"name":"台北","admin1":"台湾省","lat":25.0330,"lon":121.5654,"country":"中国"},
  {"name":"新北","admin1":"台湾省","lat":25.0110,"lon":121.4656,"country":"中国"},
  {"name":"桃园","admin1":"台湾省","lat":24.9936,"lon":121.3010,"country":"中国"},
  {"name":"台中","admin1":"台湾省","lat":24.1477,"lon":120.6736,"country":"中国"},
  {"name":"台南","admin1":"台湾省","lat":22.9997,"lon":120.2270,"country":"中国"},
  {"name":"高雄","admin1":"台湾省","lat":22.6273,"lon":120.3014,"country":"中国"}
]
